pysalad-0.1.8.data/scripts/pysalad
salad/__init__.py
salad/api.py
salad/config.py
salad/jira.py
salad/template.py
salad/test/__init__.py
salad/test/test_api.py
pysalad-0.1.8.dist-info/LICENSE
pysalad-0.1.8.dist-info/METADATA
pysalad-0.1.8.dist-info/WHEEL
pysalad-0.1.8.dist-info/top_level.txt
pysalad-0.1.8.dist-info/RECORD
