Metadata-Version: 2.1
Name: pysalad
Version: 0.1.8
Summary: just python salad
Home-page: https://github.com/hehu80/pysalad
Author: Henning Voss
Author-email: henning@huhehu.com
License: UNKNOWN
Project-URL: Bug Tracker, https://github.com/hehu80/pysalad/issues
Platform: UNKNOWN
Classifier: Programming Language :: Python :: 3
Classifier: License :: OSI Approved :: MIT License
Classifier: Operating System :: OS Independent
Requires-Python: >=3.9
License-File: LICENSE
